setup.py
grammaregex/__init__.py
grammaregex/grammaregex.py
grammaregex.egg-info/PKG-INFO
grammaregex.egg-info/SOURCES.txt
grammaregex.egg-info/dependency_links.txt
grammaregex.egg-info/requires.txt
grammaregex.egg-info/top_level.txt
grammaregex.egg-info/zip-safe