Metadata-Version: 1.1
Name: grammaregex
Version: 0.1.3
Summary: grammaregex - library for matching and finding tree sentence in regex-like way
Home-page: https://github.com/krzysiekfonal/grammaregex
Author: Krzysztof Fonal
Author-email: krzysiek.fonal@gmail.com
License: MIT
Keywords: nlp text mining text extraction
Platform: UNKNOWN
Classifier: Development Status :: 3 - Alpha
Classifier: License :: OSI Approved :: MIT License
Classifier: Programming Language :: Python :: 3.5
Classifier: Topic :: Scientific/Engineering :: Artificial Intelligence
Classifier: Intended Audience :: Science/Research
